blockstack_recover/__init__.py
blockstack_recover/recover.py
blockstack_recover-1.1.2.dist-info/LICENSE
blockstack_recover-1.1.2.dist-info/METADATA
blockstack_recover-1.1.2.dist-info/WHEEL
blockstack_recover-1.1.2.dist-info/entry_points.txt
blockstack_recover-1.1.2.dist-info/top_level.txt
blockstack_recover-1.1.2.dist-info/RECORD
