Metadata-Version: 2.1
Name: blockstack-recover
Version: 1.1.2
Summary: Wallet recovery tool for blockstack-client legacy wallets
Home-page: https://github.com/ZenulAbidin/blockstack_recover
Author: Ali Sherief
Author-email: alihsherief@linuxmail.org
License: GPLv3
Download-URL: https://github.com/ZenulAbidin/blockstack_recover/archive/master.zip
Keywords: blockchain bitcoin btc cryptocurrency name key value store data
Platform: UNKNOWN
Classifier: Intended Audience :: Developers
Classifier: License :: OSI Approved :: GNU General Public License v3 (GPLv3)
Classifier: Operating System :: OS Independent
Classifier: Programming Language :: Python :: 2 :: Only
Classifier: Topic :: Internet
Classifier: Topic :: Security :: Cryptography
Classifier: Topic :: Software Development :: Libraries :: Python Modules
Requires-Dist: base58 (==2.1.0)
Requires-Dist: bitcoin (==1.1.42)
Requires-Dist: blockstack-recover (==1.0.0)
Requires-Dist: cachetools (==4.2.1)
Requires-Dist: ecdsa (==0.16.1)
Requires-Dist: pycrypto (==2.6.1)
Requires-Dist: six (==1.15.0)
Requires-Dist: utilitybelt (==0.2.6)
